appBanco/__init__.py
appBanco/banco.py
appBanco/interface.py
appBanco/main.py
appbanco-0.1.1.dist-info/METADATA
appbanco-0.1.1.dist-info/WHEEL
appbanco-0.1.1.dist-info/entry_points.txt
appbanco-0.1.1.dist-info/top_level.txt
appbanco-0.1.1.dist-info/RECORD
