Metadata-Version: 2.4
Name: appBanco
Version: 0.1.1
Summary: Simulador simples de banco em Python
Author: K-Campassi
Dynamic: author
Dynamic: description
Dynamic: description-content-type
Dynamic: summary
